{
    "Bedroom|卧室": "(Bedroom: 1.4)",
    "Living Room|起居室": "(Living Room: 1.4)",
    "Dining Room|餐厅": "(Dining Room: 1.4)",
    "Kitchen|厨房": "(Kitchen: 1.4)",
    "Bathroom|卫生间": "(Bathroom: 1.4)",
    "Study Room|书房": "(Study: 1.4)",
    "Children's Room|儿童房": "(Children's Room: 1.4)",
    "Closet|衣柜": "(Closet: 1.4)",
    "Hallway|走廊": "(Hallway: 1.4)",
    "Laundry Room|洗衣房": "(Laundry Room: 1.4)",
    "Garage|车库": "(Garage: 1.4)",
    "Storage Room|储藏室": "(Storage Room: 1.4)",
    "Game Room|游戏室": "(Game Room: 1.4)",
    "Balcony|阳台": "(Balcony: 1.4)",
    "Terrace|室外露台": "(Terrace: 1.4)",
    "Basement|地下室": "(Basement: 1.4)",
    "Attic|阁楼": "(Attic: 1.4)",
    "Powder Room|梳妆室": "(Powder Room: 1.4)",
    "Gallery|画廊": "(Gallery: 1.4)",
    "Yoga Room|瑜伽室": "(Yoga Room: 1.4)",
    "Studio|工作室": "(Studio: 1.4)",
    "Music Room|音乐室": "(Music Room: 1.4)",
    "Home Theater|家庭影院": "(Home Theater: 1.4)",
    "Conservatory|花房": "(Conservatory: 1.4)",
    "Greenhouse|温室": "(Greenhouse: 1.4)",
    "Wine Cellar|酒窖": "(Wine Cellar: 1.4)",
    "Gym|健身房": "(Gym: 1.4)",
    "Pool House|泳池房": "(Pool House: 1.4)",
    "Reception Room|接待厅": "(Reception Room: 1.4)",
    "Office|办公室": "(Office: 1.4)",
    "Auditorium|会议室":"(auditorium:1.4)"
}